{
  "entityType" : "DEVICE",
  "entity" : {
    "additionalInfo" : {
      "description" : ""
    },
    "customerId" : {
      "entityType" : "CUSTOMER",
      "id" : "13814000-1dd2-11b2-8080-808080808080"
    },
    "deviceData" : {
      "configuration" : {
        "type" : "DEFAULT"
      },
      "transportConfiguration" : {
        "type" : "DEFAULT"
      }
    },
    "deviceProfileId" : {
      "entityType" : "DEVICE_PROFILE",
      "id" : "464cd5f0-b2da-11ef-8c91-7baf5304b8d0"
    },
    "externalId" : null,
    "firmwareId" : null,
    "id" : {
      "entityType" : "DEVICE",
      "id" : "25003f00-b30b-11ef-8c91-7baf5304b8d0"
    },
    "label" : null,
    "name" : "Demo Device 1",
    "ownerId" : null,
    "softwareId" : null,
    "type" : "Tag"
  },
  "credentials" : {
    "credentialsId" : "AxrseuZaFw9UQRUaP7QY",
    "credentialsType" : "ACCESS_TOKEN",
    "credentialsValue" : null
  },
  "relations" : [ {
    "additionalInfo" : null,
    "from" : {
      "entityType" : "ASSET",
      "id" : "903e5130-b30b-11ef-8c91-7baf5304b8d0"
    },
    "to" : {
      "entityType" : "DEVICE",
      "id" : "25003f00-b30b-11ef-8c91-7baf5304b8d0"
    },
    "type" : "DeviceToAsset",
    "typeGroup" : "COMMON",
    "version" : 82356
  }, {
    "additionalInfo" : null,
    "from" : {
      "entityType" : "ASSET",
      "id" : "6adb6d00-b6d1-11ef-838c-5dd5db96bde1"
    },
    "to" : {
      "entityType" : "DEVICE",
      "id" : "25003f00-b30b-11ef-8c91-7baf5304b8d0"
    },
    "type" : "AlarmConfigToDevice",
    "typeGroup" : "COMMON",
    "version" : 76129
  } ],
  "attributes" : {
    "SERVER_SCOPE" : [ {
      "booleanValue" : true,
      "doubleValue" : null,
      "jsonValue" : null,
      "key" : "active",
      "lastUpdateTs" : 1734008795480,
      "longValue" : null,
      "strValue" : null
    }, {
      "booleanValue" : null,
      "doubleValue" : null,
      "jsonValue" : "{}",
      "key" : "areaAlarmRules",
      "lastUpdateTs" : 1733819602977,
      "longValue" : null,
      "strValue" : null
    }, {
      "booleanValue" : true,
      "doubleValue" : null,
      "jsonValue" : null,
      "key" : "assignedAlarmProfile",
      "lastUpdateTs" : 1733819602977,
      "longValue" : null,
      "strValue" : null
    }, {
      "booleanValue" : null,
      "doubleValue" : null,
      "jsonValue" : null,
      "key" : "configPreset",
      "lastUpdateTs" : 1733404595829,
      "longValue" : null,
      "strValue" : "Default config"
    }, {
      "booleanValue" : null,
      "doubleValue" : null,
      "jsonValue" : null,
      "key" : "connectivity",
      "lastUpdateTs" : 1733404595829,
      "longValue" : null,
      "strValue" : "RFID (MQTT)"
    }, {
      "booleanValue" : null,
      "doubleValue" : null,
      "jsonValue" : null,
      "key" : "description",
      "lastUpdateTs" : 1733404595829,
      "longValue" : null,
      "strValue" : ""
    }, {
      "booleanValue" : null,
      "doubleValue" : null,
      "jsonValue" : "{}",
      "key" : "geofenceThresolds",
      "lastUpdateTs" : 1733819133211,
      "longValue" : null,
      "strValue" : null
    }, {
      "booleanValue" : true,
      "doubleValue" : null,
      "jsonValue" : null,
      "key" : "hasRelatedAsset",
      "lastUpdateTs" : 1733404771797,
      "longValue" : null,
      "strValue" : null
    }, {
      "booleanValue" : null,
      "doubleValue" : null,
      "jsonValue" : null,
      "key" : "inactivityAlarmTime",
      "lastUpdateTs" : 1734007973134,
      "longValue" : 1734007973133,
      "strValue" : null
    }, {
      "booleanValue" : null,
      "doubleValue" : null,
      "jsonValue" : "{\"id\":\"25003f00-b30b-11ef-8c91-7baf5304b8d0\",\"name\":\"Demo Asset 1\"}",
      "key" : "info",
      "lastUpdateTs" : 1733913799404,
      "longValue" : null,
      "strValue" : null
    }, {
      "booleanValue" : true,
      "doubleValue" : null,
      "jsonValue" : null,
      "key" : "isAssigned",
      "lastUpdateTs" : 1733913799404,
      "longValue" : null,
      "strValue" : null
    }, {
      "booleanValue" : null,
      "doubleValue" : null,
      "jsonValue" : null,
      "key" : "lastActivityTime",
      "lastUpdateTs" : 1734518647692,
      "longValue" : 1734518647143,
      "strValue" : null
    }, {
      "booleanValue" : null,
      "doubleValue" : null,
      "jsonValue" : null,
      "key" : "lastConnectTime",
      "lastUpdateTs" : 1734442675242,
      "longValue" : 1734442675242,
      "strValue" : null
    }, {
      "booleanValue" : null,
      "doubleValue" : null,
      "jsonValue" : null,
      "key" : "lastDisconnectTime",
      "lastUpdateTs" : 1734442633112,
      "longValue" : 1734442633112,
      "strValue" : null
    }, {
      "booleanValue" : null,
      "doubleValue" : null,
      "jsonValue" : null,
      "key" : "modelNumber",
      "lastUpdateTs" : 1733404595829,
      "longValue" : null,
      "strValue" : "Demo Device 1"
    }, {
      "booleanValue" : null,
      "doubleValue" : null,
      "jsonValue" : null,
      "key" : "serialNumber",
      "lastUpdateTs" : 1733404595829,
      "longValue" : null,
      "strValue" : "Demo Device 1"
    }, {
      "booleanValue" : null,
      "doubleValue" : null,
      "jsonValue" : "{}",
      "key" : "zoneThresolds",
      "lastUpdateTs" : 1733819602977,
      "longValue" : null,
      "strValue" : null
    } ],
    "SHARED_SCOPE" : [ ]
  }
}