{
  "entityType" : "DEVICE",
  "entity" : {
    "additionalInfo" : {
      "description" : ""
    },
    "customerId" : {
      "entityType" : "CUSTOMER",
      "id" : "13814000-1dd2-11b2-8080-808080808080"
    },
    "deviceData" : {
      "configuration" : {
        "type" : "DEFAULT"
      },
      "transportConfiguration" : {
        "type" : "DEFAULT"
      }
    },
    "deviceProfileId" : {
      "entityType" : "DEVICE_PROFILE",
      "id" : "464cd5f0-b2da-11ef-8c91-7baf5304b8d0"
    },
    "externalId" : null,
    "firmwareId" : null,
    "id" : {
      "entityType" : "DEVICE",
      "id" : "592788b0-b30b-11ef-8c91-7baf5304b8d0"
    },
    "label" : null,
    "name" : "Demo Device 5",
    "ownerId" : null,
    "softwareId" : null,
    "type" : "Tag"
  },
  "credentials" : {
    "credentialsId" : "g1wLlK5C6jt6IrDOv9F6",
    "credentialsType" : "ACCESS_TOKEN",
    "credentialsValue" : null
  },
  "relations" : [ {
    "additionalInfo" : null,
    "from" : {
      "entityType" : "ASSET",
      "id" : "b8eda950-b30b-11ef-8c91-7baf5304b8d0"
    },
    "to" : {
      "entityType" : "DEVICE",
      "id" : "592788b0-b30b-11ef-8c91-7baf5304b8d0"
    },
    "type" : "DeviceToAsset",
    "typeGroup" : "COMMON",
    "version" : 82341
  }, {
    "additionalInfo" : null,
    "from" : {
      "entityType" : "ASSET",
      "id" : "f8d6f780-b6dd-11ef-838c-5dd5db96bde1"
    },
    "to" : {
      "entityType" : "DEVICE",
      "id" : "592788b0-b30b-11ef-8c91-7baf5304b8d0"
    },
    "type" : "AlarmConfigToDevice",
    "typeGroup" : "COMMON",
    "version" : 77736
  } ],
  "attributes" : {
    "SERVER_SCOPE" : [ {
      "booleanValue" : true,
      "doubleValue" : null,
      "jsonValue" : null,
      "key" : "active",
      "lastUpdateTs" : 1734008795458,
      "longValue" : null,
      "strValue" : null
    }, {
      "booleanValue" : null,
      "doubleValue" : null,
      "jsonValue" : "{\"978e0480-b63a-11ef-838c-5dd5db96bde1\":{\"name\":\"Artemii Zone\",\"status\":\"inside\"}}",
      "key" : "areaAlarmRules",
      "lastUpdateTs" : 1733903870550,
      "longValue" : null,
      "strValue" : null
    }, {
      "booleanValue" : true,
      "doubleValue" : null,
      "jsonValue" : null,
      "key" : "assignedAlarmProfile",
      "lastUpdateTs" : 1733829143107,
      "longValue" : null,
      "strValue" : null
    }, {
      "booleanValue" : null,
      "doubleValue" : null,
      "jsonValue" : null,
      "key" : "configPreset",
      "lastUpdateTs" : 1733404682948,
      "longValue" : null,
      "strValue" : "Default config"
    }, {
      "booleanValue" : null,
      "doubleValue" : null,
      "jsonValue" : null,
      "key" : "connectivity",
      "lastUpdateTs" : 1733404682948,
      "longValue" : null,
      "strValue" : "RFID (MQTT)"
    }, {
      "booleanValue" : null,
      "doubleValue" : null,
      "jsonValue" : null,
      "key" : "description",
      "lastUpdateTs" : 1733404682948,
      "longValue" : null,
      "strValue" : ""
    }, {
      "booleanValue" : false,
      "doubleValue" : null,
      "jsonValue" : null,
      "key" : "equalThresholdBatteryLevelEnabled",
      "lastUpdateTs" : 1733831367583,
      "longValue" : null,
      "strValue" : null
    }, {
      "booleanValue" : true,
      "doubleValue" : null,
      "jsonValue" : null,
      "key" : "equalThresholdTemperatureEnabled",
      "lastUpdateTs" : 1733831367583,
      "longValue" : null,
      "strValue" : null
    }, {
      "booleanValue" : null,
      "doubleValue" : null,
      "jsonValue" : "{}",
      "key" : "geofenceThresolds",
      "lastUpdateTs" : 1733819133208,
      "longValue" : null,
      "strValue" : null
    }, {
      "booleanValue" : true,
      "doubleValue" : null,
      "jsonValue" : null,
      "key" : "hasRelatedAsset",
      "lastUpdateTs" : 1733404840066,
      "longValue" : null,
      "strValue" : null
    }, {
      "booleanValue" : false,
      "doubleValue" : null,
      "jsonValue" : null,
      "key" : "idleEnabled",
      "lastUpdateTs" : 1733831367583,
      "longValue" : null,
      "strValue" : null
    }, {
      "booleanValue" : null,
      "doubleValue" : null,
      "jsonValue" : null,
      "key" : "inactivityAlarmTime",
      "lastUpdateTs" : 1734007973134,
      "longValue" : 1734007973133,
      "strValue" : null
    }, {
      "booleanValue" : null,
      "doubleValue" : null,
      "jsonValue" : "{\"id\":\"592788b0-b30b-11ef-8c91-7baf5304b8d0\",\"name\":\"Demo Asset 5\"}",
      "key" : "info",
      "lastUpdateTs" : 1733913738208,
      "longValue" : null,
      "strValue" : null
    }, {
      "booleanValue" : true,
      "doubleValue" : null,
      "jsonValue" : null,
      "key" : "isAssigned",
      "lastUpdateTs" : 1733913738208,
      "longValue" : null,
      "strValue" : null
    }, {
      "booleanValue" : null,
      "doubleValue" : null,
      "jsonValue" : null,
      "key" : "lastActivityTime",
      "lastUpdateTs" : 1734518647703,
      "longValue" : 1734518647144,
      "strValue" : null
    }, {
      "booleanValue" : null,
      "doubleValue" : null,
      "jsonValue" : null,
      "key" : "lastConnectTime",
      "lastUpdateTs" : 1734442675251,
      "longValue" : 1734442675251,
      "strValue" : null
    }, {
      "booleanValue" : null,
      "doubleValue" : null,
      "jsonValue" : null,
      "key" : "lastDisconnectTime",
      "lastUpdateTs" : 1734442633473,
      "longValue" : 1734442633473,
      "strValue" : null
    }, {
      "booleanValue" : false,
      "doubleValue" : null,
      "jsonValue" : null,
      "key" : "lowerThresholdBatteryLevelEnabled",
      "lastUpdateTs" : 1733831367583,
      "longValue" : null,
      "strValue" : null
    }, {
      "booleanValue" : true,
      "doubleValue" : null,
      "jsonValue" : null,
      "key" : "lowerThresholdTemperatureEnabled",
      "lastUpdateTs" : 1733831367583,
      "longValue" : null,
      "strValue" : null
    }, {
      "booleanValue" : null,
      "doubleValue" : null,
      "jsonValue" : null,
      "key" : "modelNumber",
      "lastUpdateTs" : 1733404682948,
      "longValue" : null,
      "strValue" : "Demo Device 5"
    }, {
      "booleanValue" : false,
      "doubleValue" : null,
      "jsonValue" : null,
      "key" : "movementEnabled",
      "lastUpdateTs" : 1733831367583,
      "longValue" : null,
      "strValue" : null
    }, {
      "booleanValue" : null,
      "doubleValue" : null,
      "jsonValue" : null,
      "key" : "serialNumber",
      "lastUpdateTs" : 1733404682948,
      "longValue" : null,
      "strValue" : "Demo Device 5"
    }, {
      "booleanValue" : false,
      "doubleValue" : null,
      "jsonValue" : null,
      "key" : "upperThresholdBatteryLevelEnabled",
      "lastUpdateTs" : 1733831367583,
      "longValue" : null,
      "strValue" : null
    }, {
      "booleanValue" : true,
      "doubleValue" : null,
      "jsonValue" : null,
      "key" : "upperThresholdTemperatureEnabled",
      "lastUpdateTs" : 1733831367583,
      "longValue" : null,
      "strValue" : null
    }, {
      "booleanValue" : null,
      "doubleValue" : null,
      "jsonValue" : "{\"978e0480-b63a-11ef-838c-5dd5db96bde1\":{\"minInsideDuration\":23}}",
      "key" : "zoneThresolds",
      "lastUpdateTs" : 1733903870550,
      "longValue" : null,
      "strValue" : null
    } ],
    "SHARED_SCOPE" : [ ]
  }
}