{
  "entityType" : "DEVICE",
  "entity" : {
    "additionalInfo" : {
      "gateway" : false,
      "overwriteActivityTime" : false,
      "description" : ""
    },
    "customerId" : {
      "entityType" : "CUSTOMER",
      "id" : "13814000-1dd2-11b2-8080-808080808080"
    },
    "deviceData" : {
      "configuration" : {
        "type" : "DEFAULT"
      },
      "transportConfiguration" : {
        "type" : "DEFAULT"
      }
    },
    "deviceProfileId" : {
      "entityType" : "DEVICE_PROFILE",
      "id" : "e6712250-6539-11ef-9a16-c37bf92a3a90"
    },
    "externalId" : null,
    "firmwareId" : null,
    "id" : {
      "entityType" : "DEVICE",
      "id" : "6f498f40-6aa3-11ef-9d56-a967fa43ae4a"
    },
    "label" : "",
    "name" : "Device 2 (without relations)",
    "ownerId" : null,
    "softwareId" : null,
    "type" : "default"
  },
  "credentials" : {
    "credentialsId" : "hy6PfwbbL1rLGpGsME9K",
    "credentialsType" : "ACCESS_TOKEN",
    "credentialsValue" : null
  },
  "relations" : [ ],
  "attributes" : {
    "SERVER_SCOPE" : [ {
      "booleanValue" : false,
      "doubleValue" : null,
      "jsonValue" : null,
      "key" : "active",
      "lastUpdateTs" : 1725444201712,
      "longValue" : null,
      "strValue" : null
    }, {
      "booleanValue" : null,
      "doubleValue" : null,
      "jsonValue" : null,
      "key" : "inactivityAlarmTime",
      "lastUpdateTs" : 1725444201712,
      "longValue" : 1725444201709,
      "strValue" : null
    } ],
    "SHARED_SCOPE" : [ ]
  }
}